<?xml version="1.0" ?>
<Root_Node UI_File_Name="FamilyWishingWell.xml">
	<Style Style="65536" />
	<BaseWndProperty WindowID="1" WindowHeight="243" WindowWidth="305">
		<BackGroundMap BGmap="uiobj18.dds">
			<NorUV NorUVLeft="546" NorUVTop="76" NorUVWidth="243" NorUVHeight="305" />
		</BackGroundMap>
		<Container_Node Child_Cnt="40">
			<Style CtrlType="536870912" />
			<BaseWndProperty WindowID="4001" WindowLeft="13" WindowTop="63" WindowHeight="32" WindowWidth="32" Visible="1">
				<BackGroundMap BGmap="Slot32.dds">
					<NorUV NorUVWidth="32" NorUVHeight="32" />
				</BackGroundMap>
				<SlotNode />
			</BaseWndProperty>
			<Style CtrlType="536870912" />
			<BaseWndProperty WindowID="4002" WindowLeft="50" WindowTop="63" WindowHeight="32" WindowWidth="32" Visible="1">
				<BackGroundMap BGmap="Slot32.dds">
					<NorUV NorUVWidth="32" NorUVHeight="32" />
				</BackGroundMap>
				<SlotNode />
			</BaseWndProperty>
			<Style CtrlType="536870912" />
			<BaseWndProperty WindowID="4003" WindowLeft="87" WindowTop="63" WindowHeight="32" WindowWidth="32" Visible="1">
				<BackGroundMap BGmap="Slot32.dds">
					<NorUV NorUVWidth="32" NorUVHeight="32" />
				</BackGroundMap>
				<SlotNode />
			</BaseWndProperty>
			<Style CtrlType="536870912" />
			<BaseWndProperty WindowID="4004" WindowLeft="124" WindowTop="63" WindowHeight="32" WindowWidth="32" Visible="1">
				<BackGroundMap BGmap="Slot32.dds">
					<NorUV NorUVWidth="32" NorUVHeight="32" />
				</BackGroundMap>
				<SlotNode />
			</BaseWndProperty>
			<Style CtrlType="536870912" />
			<BaseWndProperty WindowID="4005" WindowLeft="161" WindowTop="63" WindowHeight="32" WindowWidth="32" Visible="1">
				<BackGroundMap BGmap="Slot32.dds">
					<NorUV NorUVWidth="32" NorUVHeight="32" />
				</BackGroundMap>
				<SlotNode />
			</BaseWndProperty>
			<Style CtrlType="536870912" />
			<BaseWndProperty WindowID="4006" WindowLeft="198" WindowTop="63" WindowHeight="32" WindowWidth="32" Visible="1">
				<BackGroundMap BGmap="Slot32.dds">
					<NorUV NorUVWidth="32" NorUVHeight="32" />
				</BackGroundMap>
				<SlotNode />
			</BaseWndProperty>
			<Style CtrlType="536870912" />
			<BaseWndProperty WindowID="4007" WindowLeft="198" WindowTop="100" WindowHeight="32" WindowWidth="32" Visible="1">
				<BackGroundMap BGmap="Slot32.dds">
					<NorUV NorUVWidth="32" NorUVHeight="32" />
				</BackGroundMap>
				<SlotNode />
			</BaseWndProperty>
			<Style CtrlType="536870912" />
			<BaseWndProperty WindowID="4008" WindowLeft="198" WindowTop="137" WindowHeight="32" WindowWidth="32" Visible="1">
				<BackGroundMap BGmap="Slot32.dds">
					<NorUV NorUVWidth="32" NorUVHeight="32" />
				</BackGroundMap>
				<SlotNode />
			</BaseWndProperty>
			<Style CtrlType="536870912" />
			<BaseWndProperty WindowID="4009" WindowLeft="198" WindowTop="174" WindowHeight="32" WindowWidth="32" Visible="1">
				<BackGroundMap BGmap="Slot32.dds">
					<NorUV NorUVWidth="32" NorUVHeight="32" />
				</BackGroundMap>
				<SlotNode />
			</BaseWndProperty>
			<Style CtrlType="536870912" />
			<BaseWndProperty WindowID="4010" WindowLeft="198" WindowTop="211" WindowHeight="32" WindowWidth="32" Visible="1">
				<BackGroundMap BGmap="Slot32.dds">
					<NorUV NorUVWidth="32" NorUVHeight="32" />
				</BackGroundMap>
				<SlotNode />
			</BaseWndProperty>
			<Style CtrlType="536870912" />
			<BaseWndProperty WindowID="4011" WindowLeft="161" WindowTop="211" WindowHeight="32" WindowWidth="32" Visible="1">
				<BackGroundMap BGmap="Slot32.dds">
					<NorUV NorUVWidth="32" NorUVHeight="32" />
				</BackGroundMap>
				<SlotNode />
			</BaseWndProperty>
			<Style CtrlType="536870912" />
			<BaseWndProperty WindowID="4012" WindowLeft="124" WindowTop="211" WindowHeight="32" WindowWidth="32" Visible="1">
				<BackGroundMap BGmap="Slot32.dds">
					<NorUV NorUVWidth="32" NorUVHeight="32" />
				</BackGroundMap>
				<SlotNode />
			</BaseWndProperty>
			<Style CtrlType="536870912" />
			<BaseWndProperty WindowID="4013" WindowLeft="87" WindowTop="211" WindowHeight="32" WindowWidth="32" Visible="1">
				<BackGroundMap BGmap="Slot32.dds">
					<NorUV NorUVWidth="32" NorUVHeight="32" />
				</BackGroundMap>
				<SlotNode />
			</BaseWndProperty>
			<Style CtrlType="536870912" />
			<BaseWndProperty WindowID="4014" WindowLeft="50" WindowTop="211" WindowHeight="32" WindowWidth="32" Visible="1">
				<BackGroundMap BGmap="Slot32.dds">
					<NorUV NorUVWidth="32" NorUVHeight="32" />
				</BackGroundMap>
				<SlotNode />
			</BaseWndProperty>
			<Style CtrlType="536870912" />
			<BaseWndProperty WindowID="4015" WindowLeft="13" WindowTop="211" WindowHeight="32" WindowWidth="32" Visible="1">
				<BackGroundMap BGmap="Slot32.dds">
					<NorUV NorUVWidth="32" NorUVHeight="32" />
				</BackGroundMap>
				<SlotNode />
			</BaseWndProperty>
			<Style CtrlType="536870912" />
			<BaseWndProperty WindowID="4016" WindowLeft="13" WindowTop="174" WindowHeight="32" WindowWidth="32" Visible="1">
				<BackGroundMap BGmap="Slot32.dds">
					<NorUV NorUVWidth="32" NorUVHeight="32" />
				</BackGroundMap>
				<SlotNode />
			</BaseWndProperty>
			<Style CtrlType="536870912" />
			<BaseWndProperty WindowID="4017" WindowLeft="13" WindowTop="137" WindowHeight="32" WindowWidth="32" Visible="1">
				<BackGroundMap BGmap="Slot32.dds">
					<NorUV NorUVWidth="32" NorUVHeight="32" />
				</BackGroundMap>
				<SlotNode />
			</BaseWndProperty>
			<Style CtrlType="536870912" />
			<BaseWndProperty WindowID="4018" WindowLeft="13" WindowTop="100" WindowHeight="32" WindowWidth="32" Visible="1">
				<BackGroundMap BGmap="Slot32.dds">
					<NorUV NorUVWidth="32" NorUVHeight="32" />
				</BackGroundMap>
				<SlotNode />
			</BaseWndProperty>
			<Style CtrlType="536870912" />
			<BaseWndProperty WindowID="4019" WindowLeft="105" WindowTop="137" WindowHeight="32" WindowWidth="32" Visible="1">
				<BackGroundMap BGmap="Slot32.dds">
					<NorUV NorUVWidth="32" NorUVHeight="32" />
				</BackGroundMap>
				<SlotNode />
			</BaseWndProperty>
			<Style CtrlType="262144" />
			<BaseWndProperty WindowID="3101" WindowLeft="89" WindowTop="249" WindowHeight="64" WindowWidth="18" Visible="1">
				<BackGroundMap BGmap="main.dds">
					<NorUV NorUVLeft="536" NorUVTop="79" NorUVWidth="64" NorUVHeight="18" />
				</BackGroundMap>
				<BaseCtrlProperty FontColor="16777215" FontStyle="1" />
				<ButtonNode BtnState="0">
					<FocusUV FocusUVLeft="536" FocusUVTop="98" FocusUVWidth="64" FocusUVHeight="18" />
					<DownUV DownUVLeft="536" DownUVTop="117" DownUVWidth="64" DownUVHeight="18" />
					<DisableUV DisableUVLeft="536" DisableUVTop="136" DisableUVWidth="64" DisableUVHeight="18" />
				</ButtonNode>
			</BaseWndProperty>
			<Style CtrlType="262144" />
			<BaseWndProperty WindowID="3001" WindowLeft="228" WindowTop="6" WindowHeight="13" WindowWidth="12">
				<BackGroundMap BGmap="main.dds">
					<NorUV NorUVLeft="618" NorUVTop="64" NorUVWidth="13" NorUVHeight="12" />
				</BackGroundMap>
				<ButtonNode BtnState="0">
					<FocusUV FocusUVLeft="632" FocusUVTop="64" FocusUVWidth="13" FocusUVHeight="12" />
					<DownUV DownUVLeft="646" DownUVTop="64" DownUVWidth="13" DownUVHeight="12" />
				</ButtonNode>
			</BaseWndProperty>
			<Style CtrlType="262144" />
			<BaseWndProperty WindowID="3002" WindowLeft="209" WindowTop="3" WindowHeight="16" WindowWidth="16">
				<BackGroundMap BGmap="main.dds">
					<NorUV NorUVLeft="999" NorUVTop="71" NorUVWidth="16" NorUVHeight="16" />
				</BackGroundMap>
				<ButtonNode BtnState="0">
					<FocusUV FocusUVLeft="999" FocusUVTop="88" FocusUVWidth="16" FocusUVHeight="16" />
					<DownUV DownUVLeft="999" DownUVTop="105" DownUVWidth="16" DownUVHeight="16" />
					<DisableUV DisableUVLeft="999" DisableUVTop="122" DisableUVWidth="16" DisableUVHeight="16" />
				</ButtonNode>
			</BaseWndProperty>
			<Style CtrlType="33554432" />
			<BaseWndProperty WindowID="2503" WindowLeft="121" WindowTop="191" WindowHeight="0" WindowWidth="0">
				<BaseCtrlProperty FontColor="16777215" FontStyle="0" />
				<TextNode TextAlign="1" MultiLine="0" />
			</BaseWndProperty>
			<Style CtrlType="33554432" />
			<BaseWndProperty WindowID="2505" WindowLeft="121" WindowTop="52" WindowHeight="0" WindowWidth="0">
				<BaseCtrlProperty FontColor="16777215" FontStyle="0" />
				<TextNode TextAlign="1" MultiLine="0" />
			</BaseWndProperty>
			<Style CtrlType="33554432" />
			<BaseWndProperty WindowID="2502" WindowLeft="121" WindowTop="39" WindowHeight="0" WindowWidth="0">
				<BaseCtrlProperty FontColor="16777215" FontStyle="0" />
				<TextNode TextAlign="1" MultiLine="0" />
			</BaseWndProperty>
			<Style CtrlType="33554432" />
			<BaseWndProperty WindowID="2501" WindowLeft="12" WindowTop="12" WindowHeight="0" WindowWidth="0">
				<BaseCtrlProperty FontColor="16777215" FontStyle="1" />
				<TextNode TextAlign="0" MultiLine="0" />
			</BaseWndProperty>
		</Container_Node>
	</BaseWndProperty>
</Root_Node>
